musint/__init__.py
musint/datasets/__init__.py
musint/datasets/amass_dataset.py
musint/datasets/babel_dataset.py
musint/datasets/humanml3d_index.csv
musint/datasets/mint_dataset.py
musint/utils/__init__.py
musint/utils/dataframe_utils.py
musint/utils/metadata_utils.py
musint/utils/hml3d_utils/__init__.py
musint/utils/hml3d_utils/humanml3d_utils.py
musint/utils/hml3d_utils/paramUtil.py
musint/utils/hml3d_utils/common/__init__.py
musint/utils/hml3d_utils/common/quaternion.py
musint/utils/hml3d_utils/common/skeleton.py
musint-0.3.0.dist-info/LICENSE
musint-0.3.0.dist-info/METADATA
musint-0.3.0.dist-info/WHEEL
musint-0.3.0.dist-info/top_level.txt
musint-0.3.0.dist-info/RECORD
