Metadata-Version: 2.1
Name: musint
Version: 0.3.0
Summary: Package for structured access to the Muscles in Time dataset.
Author: Marco Kugler
Author-email: David Schneider <david.schneider@kit.edu>
License: MIT License
Project-URL: Homepage, https://github.com/simplexsigil/MusclesInTime.git
Keywords: Muscle Activation,MinT,Muscles in Time,Dataset
Classifier: License :: OSI Approved :: MIT License
Classifier: Programming Language :: Python
Classifier: Programming Language :: Python :: 3
Requires-Python: >=3.6
License-File: LICENSE
Requires-Dist: numpy
Requires-Dist: pandas
Requires-Dist: torch
Requires-Dist: scipy
Requires-Dist: tqdm
